mac.v
// Simple mac that blasts 100 byte frames at 100mbps
module mac (
	input clk,
	input crs_dv,
	input [1:0] rx_data,
	output tx_en,
	output [1:0] tx_data,
	input rx_err
);

  // Define state enum
  typedef enum logic [1:0] { PREAMBLE, SFD_1, SFD_2, DATA } state_t;

  // State register
  logic [1:0] state, next_state;
  logic [7:0] count = 8'b0;

  logic [7:0] data = 8'b00110011;
  logic [1:0] tx_reg;

  assign tx_en = 1'b1;
  assign tx_data = tx_reg;

  initial begin
  state = 2'b00;
  tx_reg = 2'b00;
  end

  // State machine logic
  always_ff @(posedge clk) state <= next_state;

  // State transition logic
  always @(posedge clk)
  begin
    case (state)
      PREAMBLE: begin
        tx_reg = 2'b01;

        // Send 7 octets of preamble
        if (count == 56) begin
          next_state = SFD_1;
          count = 0;
        end else begin
          next_state = PREAMBLE;
          count = count + 1;
        end
      end

      // Send 6 bits of SFD
      SFD_1: begin
        tx_reg = 2'b01;

        if (count == 6) begin
          next_state = SFD_2;
          count = 0;
        end else begin
          next_state = SFD_1;
          count = count + 1;
        end
      end

      // Finish SFD
      SFD_2: begin
        tx_reg = 2'b11;
        next_state = DATA;
        count = 0;
      end

      // Send data
      DATA: begin
        tx_reg = data[ (count*2) +: 2 ];

        if (count == 4) begin
          next_state = PREAMBLE;
          count = 0;
        end else begin
          next_state = DATA;
          count = count + 1;
        end
      end

      default: begin
          count = 0;
          next_state = PREAMBLE;
      end

    endcase
    end
endmodule

waveform.vcd
$version Generated by VerilatedVcd $end
$timescale 1ps $end

 $scope module TOP $end
  $var wire  1 ' clk $end
  $var wire  1 ( crs_dv $end
  $var wire  2 ) rx_data [1:0] $end
  $var wire  1 , rx_err $end
  $var wire  2 + tx_data [1:0] $end
  $var wire  1 * tx_en $end
  $scope module mac $end
   $var wire  1 ' clk $end
   $var wire  8 % count [7:0] $end
   $var wire  1 ( crs_dv $end
   $var wire  8 - data [7:0] $end
   $var wire  2 $ next_state [1:0] $end
   $var wire  2 ) rx_data [1:0] $end
   $var wire  1 , rx_err $end
   $var wire  2 # state [1:0] $end
   $var wire  2 + tx_data [1:0] $end
   $var wire  1 * tx_en $end
   $var wire  2 & tx_reg [1:0] $end
  $upscope $end
 $upscope $end
$enddefinitions $end


#0
b00 #
b00 $
b00000000 %
b00 &
1'
0(
b00 )
1*
b00 +
0,
b00110011 -
#1
0'
#2
b00000001 %
b01 &
1'
b01 +
#3
0'
#4
b00000010 %
1'
#5
0'
#6
b00000011 %
1'
#7
0'
#8
b00000100 %
1'
#9
0'
#10
b00000101 %
1'
#11
0'
#12
b00000110 %
1'
#13
0'
#14
b00000111 %
1'
#15
0'
#16
b00001000 %
1'
#17
0'
#18
b00001001 %
1'
#19
0'
#20
b00001010 %
1'
#21
0'
#22
b00001011 %
1'
#23
0'
#24
b00001100 %
1'
#25
0'
#26
b00001101 %
1'
#27
0'
#28
b00001110 %
1'
#29
0'
#30
b00001111 %
1'
#31
0'
#32
b00010000 %
1'
#33
0'
#34
b00010001 %
1'
#35
0'
#36
b00010010 %
1'
#37
0'
#38
b00010011 %
1'
#39
0'
#40
b00010100 %
1'
#41
0'
#42
b00010101 %
1'
#43
0'
#44
b00010110 %
1'
#45
0'
#46
b00010111 %
1'
#47
0'
#48
b00011000 %
1'
#49
0'
#50
b00011001 %
1'
#51
0'
#52
b00011010 %
1'
#53
0'
#54
b00011011 %
1'
#55
0'
#56
b00011100 %
1'
#57
0'
#58
b00011101 %
1'
#59
0'
#60
b00011110 %
1'
#61
0'
#62
b00011111 %
1'
#63
0'
#64
b00100000 %
1'
#65
0'
#66
b00100001 %
1'
#67
0'
#68
b00100010 %
1'
#69
0'
#70
b00100011 %
1'
#71
0'
#72
b00100100 %
1'
#73
0'
#74
b00100101 %
1'
#75
0'
#76
b00100110 %
1'
#77
0'
#78
b00100111 %
1'
#79
0'
#80
b00101000 %
1'
#81
0'
#82
b00101001 %
1'
#83
0'
#84
b00101010 %
1'
#85
0'
#86
b00101011 %
1'
#87
0'
#88
b00101100 %
1'
#89
0'
#90
b00101101 %
1'
#91
0'
#92
b00101110 %
1'
#93
0'
#94
b00101111 %
1'
#95
0'
#96
b00110000 %
1'
#97
0'
#98
b00110001 %
1'
#99
0'
#100
b00110010 %
1'
#101
0'
#102
b00110011 %
1'
#103
0'
#104
b00110100 %
1'
#105
0'
#106
b00110101 %
1'
#107
0'
#108
b00110110 %
1'
#109
0'
#110
b00110111 %
1'
#111
0'
#112
b00111000 %
1'
#113
0'
#114
b01 #
b01 $
b00000000 %
1'
#115
0'
#116
b00000001 %
1'
#117
0'
#118
b00000010 %
1'
#119
0'
#120
b00000011 %
1'
#121
0'
#122
b00000100 %
1'
#123
0'
#124
b00000101 %
1'
#125
0'
#126
b00000110 %
1'
#127
0'
#128
b10 #
b10 $
b00000000 %
1'
#129
0'
#130
b11 #
b11 $
b11 &
1'
b11 +
#131
0'
#132
b00000001 %
1'
#133
0'
#134
b00000010 %
b00 &
1'
b00 +
#135
0'
#136
b00000011 %
b11 &
1'
b11 +
#137
0'
#138
b00000100 %
b00 &
1'
b00 +
#139
0'
#140
b00 #
b00 $
b00000000 %
b11 &
1'
b11 +
#141
0'
#142
b00000001 %
b01 &
1'
b01 +
#143
0'
#144
b00000010 %
1'
#145
0'
#146
b00000011 %
1'
#147
0'
#148
b00000100 %
1'
#149
0'
#150
b00000101 %
1'
#151
0'
#152
b00000110 %
1'
#153
0'
#154
b00000111 %
1'
#155
0'
#156
b00001000 %
1'
#157
0'
#158
b00001001 %
1'
#159
0'
#160
b00001010 %
1'
#161
0'
#162
b00001011 %
1'
#163
0'
#164
b00001100 %
1'
#165
0'
#166
b00001101 %
1'
#167
0'
#168
b00001110 %
1'
#169
0'
#170
b00001111 %
1'
#171
0'
#172
b00010000 %
1'
#173
0'
#174
b00010001 %
1'
#175
0'
#176
b00010010 %
1'
#177
0'
#178
b00010011 %
1'
#179
0'
#180
b00010100 %
1'
#181
0'
#182
b00010101 %
1'
#183
0'
#184
b00010110 %
1'
#185
0'
#186
b00010111 %
1'
#187
0'
#188
b00011000 %
1'
#189
0'
#190
b00011001 %
1'
#191
0'
#192
b00011010 %
1'
#193
0'
#194
b00011011 %
1'
#195
0'
#196
b00011100 %
1'
#197
0'
#198
b00011101 %
1'
#199
0'
#200
b00011110 %
1'
#201
0'
#202
b00011111 %
1'
#203
0'
#204
b00100000 %
1'
#205
0'
#206
b00100001 %
1'
#207
0'
#208
b00100010 %
1'
#209
0'
#210
b00100011 %
1'
#211
0'
#212
b00100100 %
1'
#213
0'
#214
b00100101 %
1'
#215
0'
#216
b00100110 %
1'
#217
0'
#218
b00100111 %
1'
#219
0'
#220
b00101000 %
1'
#221
0'
#222
b00101001 %
1'
#223
0'
#224
b00101010 %
1'
#225
0'
#226
b00101011 %
1'
#227
0'
#228
b00101100 %
1'
#229
0'
#230
b00101101 %
1'
#231
0'
#232
b00101110 %
1'
#233
0'
#234
b00101111 %
1'
#235
0'
#236
b00110000 %
1'
#237
0'
#238
b00110001 %
1'
#239
0'
#240
b00110010 %
1'
#241
0'
#242
b00110011 %
1'
#243
0'
#244
b00110100 %
1'
#245
0'
#246
b00110101 %
1'
#247
0'
#248
b00110110 %
1'
#249
0'
#250
b00110111 %
1'
#251
0'
#252
b00111000 %
1'
#253
0'
#254
b01 #
b01 $
b00000000 %
1'
#255
0'
#256
b00000001 %
1'
#257
0'
#258
b00000010 %
1'
#259
0'
#260
b00000011 %
1'
#261
0'
#262
b00000100 %
1'
#263
0'
#264
b00000101 %
1'
#265
0'
#266
b00000110 %
1'
#267
0'
#268
b10 #
b10 $
b00000000 %
1'
#269
0'
#270
b11 #
b11 $
b11 &
1'
b11 +
#271
0'
#272
b00000001 %
1'
#273
0'
#274
b00000010 %
b00 &
1'
b00 +
#275
0'
#276
b00000011 %
b11 &
1'
b11 +
#277
0'
#278
b00000100 %
b00 &
1'
b00 +
#279
0'
#280
b00 #
b00 $
b00000000 %
b11 &
1'
b11 +
#281
0'
#282
b00000001 %
b01 &
1'
b01 +
#283
0'
#284
b00000010 %
1'
#285
0'
#286
b00000011 %
1'
#287
0'
#288
b00000100 %
1'
#289
0'
#290
b00000101 %
1'
#291
0'
#292
b00000110 %
1'
#293
0'
#294
b00000111 %
1'
#295
0'
#296
b00001000 %
1'
#297
0'
#298
b00001001 %
1'
#299
0'
#300
b00001010 %
1'
#301
0'
#302
b00001011 %
1'
#303
0'
#304
b00001100 %
1'
#305
0'
#306
b00001101 %
1'
#307
0'
#308
b00001110 %
1'
#309
0'
#310
b00001111 %
1'
#311
0'
#312
b00010000 %
1'
#313
0'
#314
b00010001 %
1'
#315
0'
#316
b00010010 %
1'
#317
0'
#318
b00010011 %
1'
#319
0'
#320
b00010100 %
1'
#321
0'
#322
b00010101 %
1'
#323
0'
#324
b00010110 %
1'
#325
0'
#326
b00010111 %
1'
#327
0'
#328
b00011000 %
1'
#329
0'
#330
b00011001 %
1'
#331
0'
#332
b00011010 %
1'
#333
0'
#334
b00011011 %
1'
#335
0'
#336
b00011100 %
1'
#337
0'
#338
b00011101 %
1'
#339
0'
#340
b00011110 %
1'
#341
0'
#342
b00011111 %
1'
#343
0'
#344
b00100000 %
1'
#345
0'
#346
b00100001 %
1'
#347
0'
#348
b00100010 %
1'
#349
0'
#350
b00100011 %
1'
#351
0'
#352
b00100100 %
1'
#353
0'
#354
b00100101 %
1'
#355
0'
#356
b00100110 %
1'
#357
0'
#358
b00100111 %
1'
#359
0'
#360
b00101000 %
1'
#361
0'
#362
b00101001 %
1'
#363
0'
#364
b00101010 %
1'
#365
0'
#366
b00101011 %
1'
#367
0'
#368
b00101100 %
1'
#369
0'
#370
b00101101 %
1'
#371
0'
#372
b00101110 %
1'
#373
0'
#374
b00101111 %
1'
#375
0'
#376
b00110000 %
1'
#377
0'
#378
b00110001 %
1'
#379
0'
#380
b00110010 %
1'
#381
0'
#382
b00110011 %
1'
#383
0'
#384
b00110100 %
1'
#385
0'
#386
b00110101 %
1'
#387
0'
#388
b00110110 %
1'
#389
0'
#390
b00110111 %
1'
#391
0'
#392
b00111000 %
1'
#393
0'
#394
b01 #
b01 $
b00000000 %
1'
#395
0'
#396
b00000001 %
1'
#397
0'
#398
b00000010 %
1'
#399
0'
#400
b00000011 %
1'
#401
0'
#402
b00000100 %
1'
#403
0'
#404
b00000101 %
1'
#405
0'
#406
b00000110 %
1'
#407
0'
#408
b10 #
b10 $
b00000000 %
1'
#409
0'
#410
b11 #
b11 $
b11 &
1'
b11 +
#411
0'
#412
b00000001 %
1'
#413
0'
#414
b00000010 %
b00 &
1'
b00 +
#415
0'
#416
b00000011 %
b11 &
1'
b11 +
#417
0'
#418
b00000100 %
b00 &
1'
b00 +
#419
0'
#420
b00 #
b00 $
b00000000 %
b11 &
1'
b11 +
#421
0'
#422
b00000001 %
b01 &
1'
b01 +
#423
0'
#424
b00000010 %
1'
#425
0'
#426
b00000011 %
1'
#427
0'
#428
b00000100 %
1'
#429
0'
#430
b00000101 %
1'
#431
0'
#432
b00000110 %
1'
#433
0'
#434
b00000111 %
1'
#435
0'
#436
b00001000 %
1'
#437
0'
#438
b00001001 %
1'
#439
0'
#440
b00001010 %
1'
#441
0'
#442
b00001011 %
1'
#443
0'
#444
b00001100 %
1'
#445
0'
#446
b00001101 %
1'
#447
0'
#448
b00001110 %
1'
#449
0'
#450
b00001111 %
1'
#451
0'
#452
b00010000 %
1'
#453
0'
#454
b00010001 %
1'
#455
0'
#456
b00010010 %
1'
#457
0'
#458
b00010011 %
1'
#459
0'
#460
b00010100 %
1'
#461
0'
#462
b00010101 %
1'
#463
0'
#464
b00010110 %
1'
#465
0'
#466
b00010111 %
1'
#467
0'
#468
b00011000 %
1'
#469
0'
#470
b00011001 %
1'
#471
0'
#472
b00011010 %
1'
#473
0'
#474
b00011011 %
1'
#475
0'
#476
b00011100 %
1'
#477
0'
#478
b00011101 %
1'
#479
0'
#480
b00011110 %
1'
#481
0'
#482
b00011111 %
1'
#483
0'
#484
b00100000 %
1'
#485
0'
#486
b00100001 %
1'
#487
0'
#488
b00100010 %
1'
#489
0'
#490
b00100011 %
1'
#491
0'
#492
b00100100 %
1'
#493
0'
#494
b00100101 %
1'
#495
0'
#496
b00100110 %
1'
#497
0'
#498
b00100111 %
1'
