mac.v
// Simple mac that blasts 100 byte frames at 100mbps
module mac ( input clk, input crs_dv, input [1:0] rx_data, output tx_en, output reg [1:0] tx_data, input rx_err);

  typedef enum logic [1:0] { PREAMBLE, SFD_1, SFD_2, DATA } state_t;

  logic [1:0] state = PREAMBLE, next_state;
  logic [7:0] count = 8'b0;
  logic [7:0] data = 8'b11001010;

  // State machine logic
  always_ff @(posedge clk) begin
    count = (state == next_state) ? count + 1 : 0;
    state = next_state;
  end

  always_comb
    case (state)
      PREAMBLE: tx_data = 2'b01;
      SFD_1: tx_data = 2'b01;
      SFD_2: tx_data = 2'b11;
      DATA: tx_data = data[ (7-(count*2)) -: 2 ];
    endcase

  // State transition logic
  always_comb
  begin
    case (state)
      PREAMBLE: begin
        // Send 7 octets of preamble
        if (count == 27) begin
          next_state = SFD_1;
        end else begin
          next_state = PREAMBLE;
        end
      end

      // Send 6 bits of SFD
      SFD_1: begin
        if (count == 2) begin
          next_state = SFD_2;
        end else begin
          next_state = SFD_1;
        end
      end

      // Finish SFD
      SFD_2: begin
        next_state = DATA;
      end

      // Send data
      DATA: begin
        if (count == 3) begin
          next_state = PREAMBLE;
        end else begin
          next_state = DATA;
        end
      end
    endcase
    end
endmodule

waveform.vcd
$version Generated by VerilatedVcd $end
$timescale 1ps $end

 $scope module TOP $end
  $var wire  1 & clk $end
  $var wire  1 ' crs_dv $end
  $var wire  2 ( rx_data [1:0] $end
  $var wire  1 + rx_err $end
  $var wire  2 * tx_data [1:0] $end
  $var wire  1 ) tx_en $end
  $scope module mac $end
   $var wire  1 & clk $end
   $var wire  8 % count [7:0] $end
   $var wire  1 ' crs_dv $end
   $var wire  8 , data [7:0] $end
   $var wire  2 $ next_state [1:0] $end
   $var wire  2 ( rx_data [1:0] $end
   $var wire  1 + rx_err $end
   $var wire  2 # state [1:0] $end
   $var wire  2 * tx_data [1:0] $end
   $var wire  1 ) tx_en $end
  $upscope $end
 $upscope $end
$enddefinitions $end


#0
b00 #
b00 $
b00000000 %
1&
0'
b00 (
0)
b01 *
0+
b11001010 ,
#1
0&
#2
b00000001 %
1&
#3
0&
#4
b00000010 %
1&
#5
0&
#6
b00000011 %
1&
#7
0&
#8
b00000100 %
1&
#9
0&
#10
b00000101 %
1&
#11
0&
#12
b00000110 %
1&
#13
0&
#14
b00000111 %
1&
#15
0&
#16
b00001000 %
1&
#17
0&
#18
b00001001 %
1&
#19
0&
#20
b00001010 %
1&
#21
0&
#22
b00001011 %
1&
#23
0&
#24
b00001100 %
1&
#25
0&
#26
b00001101 %
1&
#27
0&
#28
b00001110 %
1&
#29
0&
#30
b00001111 %
1&
#31
0&
#32
b00010000 %
1&
#33
0&
#34
b00010001 %
1&
#35
0&
#36
b00010010 %
1&
#37
0&
#38
b00010011 %
1&
#39
0&
#40
b00010100 %
1&
#41
0&
#42
b00010101 %
1&
#43
0&
#44
b00010110 %
1&
#45
0&
#46
b00010111 %
1&
#47
0&
#48
b00011000 %
1&
#49
0&
#50
b00011001 %
1&
#51
0&
#52
b00011010 %
1&
#53
0&
#54
b01 $
b00011011 %
1&
#55
0&
#56
b01 #
b00000000 %
1&
#57
0&
#58
b00000001 %
1&
#59
0&
#60
b10 $
b00000010 %
1&
#61
0&
#62
b10 #
b11 $
b00000000 %
1&
b11 *
#63
0&
#64
b11 #
1&
#65
0&
#66
b00000001 %
1&
b00 *
#67
0&
#68
b00000010 %
1&
b10 *
#69
0&
#70
b00 $
b00000011 %
1&
#71
0&
#72
b00 #
b00000000 %
1&
b01 *
#73
0&
#74
b00000001 %
1&
#75
0&
#76
b00000010 %
1&
#77
0&
#78
b00000011 %
1&
#79
0&
#80
b00000100 %
1&
#81
0&
#82
b00000101 %
1&
#83
0&
#84
b00000110 %
1&
#85
0&
#86
b00000111 %
1&
#87
0&
#88
b00001000 %
1&
#89
0&
#90
b00001001 %
1&
#91
0&
#92
b00001010 %
1&
#93
0&
#94
b00001011 %
1&
#95
0&
#96
b00001100 %
1&
#97
0&
#98
b00001101 %
1&
#99
0&
#100
b00001110 %
1&
#101
0&
#102
b00001111 %
1&
#103
0&
#104
b00010000 %
1&
#105
0&
#106
b00010001 %
1&
#107
0&
#108
b00010010 %
1&
#109
0&
#110
b00010011 %
1&
#111
0&
#112
b00010100 %
1&
#113
0&
#114
b00010101 %
1&
#115
0&
#116
b00010110 %
1&
#117
0&
#118
b00010111 %
1&
#119
0&
#120
b00011000 %
1&
#121
0&
#122
b00011001 %
1&
#123
0&
#124
b00011010 %
1&
#125
0&
#126
b01 $
b00011011 %
1&
#127
0&
#128
b01 #
b00000000 %
1&
#129
0&
#130
b00000001 %
1&
#131
0&
#132
b10 $
b00000010 %
1&
#133
0&
#134
b10 #
b11 $
b00000000 %
1&
b11 *
#135
0&
#136
b11 #
1&
#137
0&
#138
b00000001 %
1&
b00 *
#139
0&
#140
b00000010 %
1&
b10 *
#141
0&
#142
b00 $
b00000011 %
1&
#143
0&
#144
b00 #
b00000000 %
1&
b01 *
#145
0&
#146
b00000001 %
1&
#147
0&
#148
b00000010 %
1&
#149
0&
#150
b00000011 %
1&
#151
0&
#152
b00000100 %
1&
#153
0&
#154
b00000101 %
1&
#155
0&
#156
b00000110 %
1&
#157
0&
#158
b00000111 %
1&
#159
0&
#160
b00001000 %
1&
#161
0&
#162
b00001001 %
1&
#163
0&
#164
b00001010 %
1&
#165
0&
#166
b00001011 %
1&
#167
0&
#168
b00001100 %
1&
#169
0&
#170
b00001101 %
1&
#171
0&
#172
b00001110 %
1&
#173
0&
#174
b00001111 %
1&
#175
0&
#176
b00010000 %
1&
#177
0&
#178
b00010001 %
1&
#179
0&
#180
b00010010 %
1&
#181
0&
#182
b00010011 %
1&
#183
0&
#184
b00010100 %
1&
#185
0&
#186
b00010101 %
1&
#187
0&
#188
b00010110 %
1&
#189
0&
#190
b00010111 %
1&
#191
0&
#192
b00011000 %
1&
#193
0&
#194
b00011001 %
1&
#195
0&
#196
b00011010 %
1&
#197
0&
#198
b01 $
b00011011 %
1&
#199
0&
#200
b01 #
b00000000 %
1&
#201
0&
#202
b00000001 %
1&
#203
0&
#204
b10 $
b00000010 %
1&
#205
0&
#206
b10 #
b11 $
b00000000 %
1&
b11 *
#207
0&
#208
b11 #
1&
#209
0&
#210
b00000001 %
1&
b00 *
#211
0&
#212
b00000010 %
1&
b10 *
#213
0&
#214
b00 $
b00000011 %
1&
#215
0&
#216
b00 #
b00000000 %
1&
b01 *
#217
0&
#218
b00000001 %
1&
#219
0&
#220
b00000010 %
1&
#221
0&
#222
b00000011 %
1&
#223
0&
#224
b00000100 %
1&
#225
0&
#226
b00000101 %
1&
#227
0&
#228
b00000110 %
1&
#229
0&
#230
b00000111 %
1&
#231
0&
#232
b00001000 %
1&
#233
0&
#234
b00001001 %
1&
#235
0&
#236
b00001010 %
1&
#237
0&
#238
b00001011 %
1&
#239
0&
#240
b00001100 %
1&
#241
0&
#242
b00001101 %
1&
#243
0&
#244
b00001110 %
1&
#245
0&
#246
b00001111 %
1&
#247
0&
#248
b00010000 %
1&
#249
0&
#250
b00010001 %
1&
#251
0&
#252
b00010010 %
1&
#253
0&
#254
b00010011 %
1&
#255
0&
#256
b00010100 %
1&
#257
0&
#258
b00010101 %
1&
#259
0&
#260
b00010110 %
1&
#261
0&
#262
b00010111 %
1&
#263
0&
#264
b00011000 %
1&
#265
0&
#266
b00011001 %
1&
#267
0&
#268
b00011010 %
1&
#269
0&
#270
b01 $
b00011011 %
1&
#271
0&
#272
b01 #
b00000000 %
1&
#273
0&
#274
b00000001 %
1&
#275
0&
#276
b10 $
b00000010 %
1&
#277
0&
#278
b10 #
b11 $
b00000000 %
1&
b11 *
#279
0&
#280
b11 #
1&
#281
0&
#282
b00000001 %
1&
b00 *
#283
0&
#284
b00000010 %
1&
b10 *
#285
0&
#286
b00 $
b00000011 %
1&
#287
0&
#288
b00 #
b00000000 %
1&
b01 *
#289
0&
#290
b00000001 %
1&
#291
0&
#292
b00000010 %
1&
#293
0&
#294
b00000011 %
1&
#295
0&
#296
b00000100 %
1&
#297
0&
#298
b00000101 %
1&
#299
0&
#300
b00000110 %
1&
#301
0&
#302
b00000111 %
1&
#303
0&
#304
b00001000 %
1&
#305
0&
#306
b00001001 %
1&
#307
0&
#308
b00001010 %
1&
#309
0&
#310
b00001011 %
1&
#311
0&
#312
b00001100 %
1&
#313
0&
#314
b00001101 %
1&
#315
0&
#316
b00001110 %
1&
#317
0&
#318
b00001111 %
1&
#319
0&
#320
b00010000 %
1&
#321
0&
#322
b00010001 %
1&
#323
0&
#324
b00010010 %
1&
#325
0&
#326
b00010011 %
1&
#327
0&
#328
b00010100 %
1&
#329
0&
#330
b00010101 %
1&
#331
0&
#332
b00010110 %
1&
#333
0&
#334
b00010111 %
1&
#335
0&
#336
b00011000 %
1&
#337
0&
#338
b00011001 %
1&
#339
0&
#340
b00011010 %
1&
#341
0&
#342
b01 $
b00011011 %
1&
#343
0&
#344
b01 #
b00000000 %
1&
#345
0&
#346
b00000001 %
1&
#347
0&
#348
b10 $
b00000010 %
1&
#349
0&
#350
b10 #
b11 $
b00000000 %
1&
b11 *
#351
0&
#352
b11 #
1&
#353
0&
#354
b00000001 %
1&
b00 *
#355
0&
#356
b00000010 %
1&
b10 *
#357
0&
#358
b00 $
b00000011 %
1&
#359
0&
#360
b00 #
b00000000 %
1&
b01 *
#361
0&
#362
b00000001 %
1&
#363
0&
#364
b00000010 %
1&
#365
0&
#366
b00000011 %
1&
#367
0&
#368
b00000100 %
1&
#369
0&
#370
b00000101 %
1&
#371
0&
#372
b00000110 %
1&
#373
0&
#374
b00000111 %
1&
#375
0&
#376
b00001000 %
1&
#377
0&
#378
b00001001 %
1&
#379
0&
#380
b00001010 %
1&
#381
0&
#382
b00001011 %
1&
#383
0&
#384
b00001100 %
1&
#385
0&
#386
b00001101 %
1&
#387
0&
#388
b00001110 %
1&
#389
0&
#390
b00001111 %
1&
#391
0&
#392
b00010000 %
1&
#393
0&
#394
b00010001 %
1&
#395
0&
#396
b00010010 %
1&
#397
0&
#398
b00010011 %
1&
#399
0&
#400
b00010100 %
1&
#401
0&
#402
b00010101 %
1&
#403
0&
#404
b00010110 %
1&
#405
0&
#406
b00010111 %
1&
#407
0&
#408
b00011000 %
1&
#409
0&
#410
b00011001 %
1&
#411
0&
#412
b00011010 %
1&
#413
0&
#414
b01 $
b00011011 %
1&
#415
0&
#416
b01 #
b00000000 %
1&
#417
0&
#418
b00000001 %
1&
#419
0&
#420
b10 $
b00000010 %
1&
#421
0&
#422
b10 #
b11 $
b00000000 %
1&
b11 *
#423
0&
#424
b11 #
1&
#425
0&
#426
b00000001 %
1&
b00 *
#427
0&
#428
b00000010 %
1&
b10 *
#429
0&
#430
b00 $
b00000011 %
1&
#431
0&
#432
b00 #
b00000000 %
1&
b01 *
#433
0&
#434
b00000001 %
1&
#435
0&
#436
b00000010 %
1&
#437
0&
#438
b00000011 %
1&
#439
0&
#440
b00000100 %
1&
#441
0&
#442
b00000101 %
1&
#443
0&
#444
b00000110 %
1&
#445
0&
#446
b00000111 %
1&
#447
0&
#448
b00001000 %
1&
#449
0&
#450
b00001001 %
1&
#451
0&
#452
b00001010 %
1&
#453
0&
#454
b00001011 %
1&
#455
0&
#456
b00001100 %
1&
#457
0&
#458
b00001101 %
1&
#459
0&
#460
b00001110 %
1&
#461
0&
#462
b00001111 %
1&
#463
0&
#464
b00010000 %
1&
#465
0&
#466
b00010001 %
1&
#467
0&
#468
b00010010 %
1&
#469
0&
#470
b00010011 %
1&
#471
0&
#472
b00010100 %
1&
#473
0&
#474
b00010101 %
1&
#475
0&
#476
b00010110 %
1&
#477
0&
#478
b00010111 %
1&
#479
0&
#480
b00011000 %
1&
#481
0&
#482
b00011001 %
1&
#483
0&
#484
b00011010 %
1&
#485
0&
#486
b01 $
b00011011 %
1&
#487
0&
#488
b01 #
b00000000 %
1&
#489
0&
#490
b00000001 %
1&
#491
0&
#492
b10 $
b00000010 %
1&
#493
0&
#494
b10 #
b11 $
b00000000 %
1&
b11 *
#495
0&
#496
b11 #
1&
#497
0&
#498
b00000001 %
1&
b00 *
